blender_mcp/__init__.py
blender_mcp/server.py
mseep_blender_mcp-1.2.2.dist-info/licenses/LICENSE
mseep_blender_mcp-1.2.2.dist-info/METADATA
mseep_blender_mcp-1.2.2.dist-info/WHEEL
mseep_blender_mcp-1.2.2.dist-info/entry_points.txt
mseep_blender_mcp-1.2.2.dist-info/top_level.txt
mseep_blender_mcp-1.2.2.dist-info/RECORD
