Metadata-Version: 2.4
Name: mseep-blender-mcp
Version: 1.2.2
Summary: Blender integration through the Model Context Protocol
Author-email: mseep <support@skydeck.ai>
License: MIT
Project-URL: Homepage, https://github.com/yourusername/blender-mcp
Project-URL: Bug Tracker, https://github.com/yourusername/blender-mcp/issues
Classifier: Programming Language :: Python :: 3
Classifier: License :: OSI Approved :: MIT License
Classifier: Operating System :: OS Independent
Requires-Python: >=3.10
License-File: LICENSE
Requires-Dist: mcp[cli]>=1.3.0
Dynamic: license-file
